llm_index/__init__.py
llm_index/index/__init__.py
llm_index/load/__init__.py
llm_index/load/base.py
llm_index/load/gcp/__init__.py
llm_index/load/gcp/bigquery.py
llm_index/load/gcp/storage.py
llm_index/load/local/__init__.py
llm_index/load/local/base.py
llm_index/query/__init__.py
llm_index/store/__init__.py
llm_index-0.1.0.dist-info/LICENSE
llm_index-0.1.0.dist-info/METADATA
llm_index-0.1.0.dist-info/WHEEL
llm_index-0.1.0.dist-info/RECORD
